[
  {
    "topic_or_construct": [
      "Primary response accuracy"
    ],
    "measured_by": [
      "d\u2032 (d-prime)"
    ],
    "justification": "\u201cThis model provides d\u2032 \u2014 an index of primary response accuracy\u2026\u201d"
  },
  {
    "topic_or_construct": [
      "Metacognitive accuracy",
      "Type-2 diagnosticity"
    ],
    "measured_by": [
      "meta-d\u2032"
    ],
    "justification": "\u201c\u2026meta-d\u2032 \u2014 an index that quantifies the diagnostic value of the secondary variable \u2026 regarding primary response correctness.\u201d"
  },
  {
    "topic_or_construct": [
      "Metacognitive efficiency",
      "Type-2 performance relative to accuracy"
    ],
    "measured_by": [
      "m-ratio (meta-d\u2032/d\u2032)"
    ],
    "justification": "\u201cAccordingly, we calculated meta-d\u2032/d\u2032 (known as m-ratio) to quantify type-2 performance relative to primary response accuracy.\u201d"
  }
]