[
  {
    "topic_or_construct": [
      "Empathy choice"
    ],
    "measured_by": [
      "Empathy Selection Task"
    ],
    "justification": "\"The main dependent variable for all experiments is empathy choice as measured by the Empathy Selection Task.\""
  },
  {
    "topic_or_construct": [
      "Mental demand",
      "cognitive effort"
    ],
    "measured_by": [
      "NASA Task Load Index \u2013 Mental Demand item"
    ],
    "justification": "The authors state that participants answered the NASA Task Load Index question \"How mentally demanding was this deck?\", noting that the TLX \"is an assessment of subjective cognitive costs.\""
  },
  {
    "topic_or_construct": [
      "Self-efficacy (during task)"
    ],
    "measured_by": [
      "NASA Task Load Index \u2013 Self-Efficacy item"
    ],
    "justification": "The fourth TLX question \"How successful were you in accomplishing what you were asked to do in this deck?\" is described as measuring \"self-efficacy.\""
  },
  {
    "topic_or_construct": [
      "Perceived aversiveness"
    ],
    "measured_by": [
      "NASA Task Load Index \u2013 Aversiveness item"
    ],
    "justification": "The third TLX question \"How insecure, discouraged, irritated, stressed, and annoyed were you by this deck?\" is identified by the authors as assessing \"aversiveness.\""
  },
  {
    "topic_or_construct": [
      "Dispositional empathy"
    ],
    "measured_by": [
      "Interpersonal Reactivity Index"
    ],
    "justification": "In Experiment 3a \"participants also completed the Interpersonal Reactivity Index (Davis, 1980),\" a standard trait empathy questionnaire."
  },
  {
    "topic_or_construct": [
      "Dispositional empathy"
    ],
    "measured_by": [
      "22-item Empathy Quotient"
    ],
    "justification": "Experiment 3a further reports that participants completed \"the 22-item version of the Empathy Quotient (Wakabayashi et al., 2006),\" another instrument assessing trait empathy."
  }
]