[
  {
    "topic_or_construct": "outcome-irrelevant learning",
    "measured_by": "reinforcement learning bandit task",
    "justification": "The reinforcement learning bandit task was used to estimate outcome-irrelevant learning by examining whether the outcome in the first offer affected response key selection in the second offer, indicating value assignment to irrelevant task features."
  },
  {
    "topic_or_construct": "working memory capacity",
    "measured_by": "change-detection task",
    "justification": "Working memory capacity was estimated using a well-known change-detection task, where participants had to maintain and retrieve visual information. The detection accuracy was calculated according to K = set_size \u2022 (2 \u2022 accuracy \u2013 1) for each individual."
  }
]