[
  {
    "measured_by": "1–10 rating scale (1 = extremely weak, 10 = extremely strong)",
    "justification": "\"Participants first saw the lift outcome of Round 1 and made strength judgments (1-10; 1 means extremely weak and 10 means extremely strong)…\"",
    "construct": "Perceived strength of contestants"
  },
  {
    "measured_by": "0–100% effort scale",
    "justification": "The same instruction notes that participants also \"made … effort judgments (0-100%) for each contestant.\"",
    "construct": "Perceived effort"
  },
  {
    "measured_by": "0–100% probability estimate",
    "justification": "\"For Round 2 and Round 3, they predicted the probability of the contestants lifting the box (0-100%) before seeing the outcome…\"",
    "construct": "Perceived lift probability"
  },
  {
    "measured_by": "Gini coefficient",
    "justification": "\"…we add to the cost function a Gini coefficient that penalizes unequal effort allocations.\"",
    "construct": "Inequality in effort allocation"
  }
]