[
  {
    "measured_by": "1–5 familiarity rating scale ('sure new' to 'sure old')",
    "justification": "\"Participants were asked to... rate their familiarity for each image on a continuous scale from 1-5, with labels of 'sure new,' 'unsure' and 'sure old' at the 1, 3 and 5 positions.\"",
    "construct": "Subjective familiarity"
  },
  {
    "measured_by": "Quadrant source judgment on 2×2 grid",
    "justification": "\"They were asked to click the location in which the image had previously appeared during encoding\" using \"a small gray 2 × 2 grid representing the same grid from the encoding phase.\"",
    "construct": "Source memory (recollection of encoding location)"
  },
  {
    "measured_by": "1–5 confidence rating scale ('not at all' to 'very sure')",
    "justification": "\"Participants were then asked to rate their confidence in this source judgment on a continuous scale from 1-5, with labels 'not at all,' 'somewhat' and 'very sure' at the 1, 3 and 5 positions.\"",
    "construct": "Source-confidence (metamemory confidence in source judgment)"
  }
]