[
  {
    "measured_by": "monetary costs",
    "justification": "The article states that outcome-based utility functions \"can be derived from objective measures (e.g., monetary costs).\"",
    "construct": "Outcome-based utility"
  },
  {
    "measured_by": "side effects experienced by a patient",
    "justification": "It notes that subjective measures such as \"side effects experienced by a patient\" can be used to derive these utilities.",
    "construct": "Outcome-based utility"
  },
  {
    "measured_by": "treatment benefits and harms as judged by doctors",
    "justification": "The same sentence lists \"treatment benefits and harms as judged by doctors\" as another subjective basis for measuring outcome utilities.",
    "construct": "Outcome-based utility"
  },
  {
    "measured_by": "quality-adjusted life years",
    "justification": "The authors add that a mixed measure for utilities is \"quality-adjusted life years.\"",
    "construct": "Outcome-based utility"
  }
]